README.rst
setup.cfg
setup.py
snorkel_ie/__init__.py
snorkel_ie/annotations.py
snorkel_ie/candidates.py
snorkel_ie/entity_features.py
snorkel_ie/features.py
snorkel_ie/learning.py
snorkel_ie/learning_utils.py
snorkel_ie/lf_helpers.py
snorkel_ie/loaders.py
snorkel_ie/lstm.py
snorkel_ie/matcher_utils.py
snorkel_ie/matchers.py
snorkel_ie/parser.py
snorkel_ie/queries.py
snorkel_ie/utils.py
snorkel_ie/viewer.py
snorkel_ie.egg-info/PKG-INFO
snorkel_ie.egg-info/SOURCES.txt
snorkel_ie.egg-info/dependency_links.txt
snorkel_ie.egg-info/requires.txt
snorkel_ie.egg-info/top_level.txt