Metadata-Version: 1.1
Name: snorkel-ie
Version: 0.4a0
Summary: a lightweight framework for developing structured information extraction applications
Home-page: https://github.com/HazyResearch/snorkel
Author: Alex Ratner
Author-email: ajratner@stanford.edu
License: Apache
Download-URL: https://github.com/HazyResearch/snorkel/tarball/v0.4.alpha
Keywords: information extraction
Platform: UNKNOWN
Classifier: Development Status :: 3 - Alpha
Classifier: License :: OSI Approved :: Apache Software License
Classifier: Programming Language :: Python :: 2.7
